README
setup.cfg
setup.py
ploogz/__init__.py
ploogz/ploogins.py
ploogz.egg-info/PKG-INFO
ploogz.egg-info/SOURCES.txt
ploogz.egg-info/dependency_links.txt
ploogz.egg-info/requires.txt
ploogz.egg-info/top_level.txt